auton/__init__.py
auton/classes/__init__.py
auton/classes/config.py
auton/classes/exceptions.py
auton/classes/plugins.py
auton/classes/target.py
auton/modules/__init__.py
auton/modules/job.py
auton/plugins/__init__.py
auton/plugins/subproc.py
autond-0.2.23.data/scripts/auton
autond-0.2.23.data/scripts/autond
autond-0.2.23.dist-info/LICENSE
autond-0.2.23.dist-info/METADATA
autond-0.2.23.dist-info/WHEEL
autond-0.2.23.dist-info/top_level.txt
autond-0.2.23.dist-info/RECORD
