Metadata-Version: 2.1
Name: autond
Version: 0.2.23
Summary: autond
Home-page: https://github.com/decryptus/auton
Author: Adrien Delle Cave
Author-email: pypi@doowan.net
License: License GPL-3
Platform: UNKNOWN
Classifier: License :: OSI Approved :: GNU General Public License v3 (GPLv3)
Classifier: Natural Language :: English
Classifier: Operating System :: Unix
Classifier: Programming Language :: Python
Classifier: Programming Language :: Python :: 2
Classifier: Programming Language :: Python :: 2.7
Classifier: Programming Language :: Python :: 3
Classifier: Programming Language :: Python :: 3.5
Classifier: Programming Language :: Python :: 3.6
Classifier: Programming Language :: Python :: 3.7
Classifier: Topic :: System :: Shells
Classifier: Topic :: Terminals
Classifier: Topic :: Utilities
Classifier: Topic :: Internet :: WWW/HTTP :: HTTP Servers
Requires-Python: >=2.7, !=3.0.*, !=3.1.*, !=3.2.*, !=3.3.*, !=3.4.*
Requires-Dist: PyYAML (>=3.10)
Requires-Dist: dwho (>=0.3.59)
Requires-Dist: httpdis (>=0.6.26)
Requires-Dist: pycurl
Requires-Dist: python-dotenv
Requires-Dist: requests (>=2.0)
Requires-Dist: six (>=1.13.0)
Requires-Dist: sonicprobe (>=0.3.51)
